gruvboxify/__init__.py
gruvboxify/main.py
gruvboxify-1.1.0.dist-info/LICENSE
gruvboxify-1.1.0.dist-info/METADATA
gruvboxify-1.1.0.dist-info/WHEEL
gruvboxify-1.1.0.dist-info/entry_points.txt
gruvboxify-1.1.0.dist-info/top_level.txt
gruvboxify-1.1.0.dist-info/RECORD
