Metadata-Version: 2.2
Name: gruvboxify
Version: 1.1.0
Summary: Convert images to the Gruvbox color palette
Author-email: Aditya <theveryjeff712@gmail.com>
Maintainer-email: Aditya <theveryjeff712@gmail.com>
License: MIT
Project-URL: Homepage, https://github.com/adk7712/gruvboxify
Project-URL: Bug Tracker, https://github.com/adk7712/gruvboxify/issues
Project-URL: Changelog, https://github.com/adk7712/gruvboxify/blob/master/CHANGELOG.md
Keywords: gruvbox,cli,gruvboxify,wallpaper,image,palette,color
Requires-Python: >=3.8
License-File: LICENSE
Requires-Dist: numpy>=2.2.2
Requires-Dist: Pillow>=10.0.0
